<!--If you know what You Say! references, you get a cookie. DM me at @Cosmo224 on Twitter if you get this :)-->

<IGameObjects>
	<IGameObject id="0" name="TestIGameObject" GameObjectimage="IGameObjects\TestIGameObject.png" collision="true" gravity="true" cansnap="true"></IGameObject>
	<IGameObject id="1" name="Trincid" GameObjectimage="IGameObjects\Player\TrincidStanding.png" gravity="true" hitbox="8,45,33,63" collision="true" isplayer="true" mass="1" issentient="true">
    <AssociatedScript>
    <Name>Player Core Script</Name>
    <Path>Game\Scripts\PlayerCore.esx</Path>
			<RunOn>
				<EventClass>EveryFrame</EventClass>
				<Name>RunNow</Name>
				<Parameter>
					<Name>Test</Name>
					<Value>1</Value>
				</Parameter>
			</RunOn>
    </AssociatedScript>
  </IGameObject>
	<IGameObject id="2" name="Floor" GameObjectimage="IGameObjects\FloorTEMPORARY.png" gravity="false"></IGameObject>
	<IGameObject id="3" name="Stg07 Wall/Platform Top" GameObjectimage="IGameObjects\Stg06\Stg06_wall_platform_01.png" gravity="false"></IGameObject> 
	<IGameObject id="4" name="IGameObject Priority Test" GameObjectimage="IGameObjects\TestIGameObjectPriority.png" gravity="false" priority="BG1"></IGameObject> 
	<IGameObject id="5" name="IGameObject Priority Test 2" GameObjectimage="IGameObjects\TestIGameObjectPriority2.png" gravity="false" priority="BG2"></IGameObject> 
	<IGameObject id="6" name="IGameObject Priority Test 3" GameObjectimage="IGameObjects\TestIGameObjectPriority3.png" gravity="false" priority="Low"></IGameObject> 
	<IGameObject id="7" name="IGameObject Priority Test 4" GameObjectimage="IGameObjects\TestIGameObjectPriority4.png" gravity="false" priority="Medium"></IGameObject> 
	<IGameObject id="8" name="IGameObject Priority Test 5" GameObjectimage="IGameObjects\TestIGameObjectPriority5.png" gravity="false" priority="High"></IGameObject> 
	<IGameObject id="9" name="You Say!" GameObjectimage="IGameObjects\General\Yousay.png" gravity="false" priority="Medium"></IGameObject> 
	<IGameObject id="10" name="Snap Test" GameObjectimage="IGameObjects\TestIGameObjectPriority6.png" cansnap="true" gravity="false"></IGameObject>
	<IGameObject id="11" name="Animation Test" GameObjectimage="IGameObjects\AnimationTest.png" cansnap="false" gravity="false" collision="false"></IGameObject>
	<IGameObject id="12" name="Spring" GameObjectimage="IGameObjects\Spring.png" cansnap="false" gravity="false"></IGameObject>
	<IGameObject id="13" name="Stg07 Tunnel" GameObjectimage="IGameObjects\Stg06\Stg06_tunnel_01.png" cansnap="false" gravity="false" priority="Low" hitbox="14,83,280,83"></IGameObject>
	<IGameObject id="14" name="Stg07 Wall #1" GameObjectimage="IGameObjects\Stg06\Stg06_wall_01.png" cansnap="false" gravity="false"></IGameObject>
	<IGameObject id="15" name="Stg07 Wall #2" GameObjectimage="IGameObjects\Stg06\Stg06_wall_02.png" cansnap="false" gravity="false"></IGameObject>
	<IGameObject id="16" name="Stg07 Wall #2 Top" GameObjectimage="IGameObjects\Stg06\Stg06_wall_02_top.png" cansnap="false" gravity="false"></IGameObject>
	<IGameObject id="17" name="Stg07 Toxic Water" GameObjectimage="IGameObjects\Stg06\Stg06_toxic_water_01_idle.png" cansnap="false" collision="false" priority="High"></IGameObject>
	<IGameObject id="18" name="Stg07 Chemical Disposal" GameObjectimage="IGameObjects\Stg06\Stg06_chemicaldisposal_02.png" cansnap="false" collision="false"></IGameObject>
	<IGameObject id="19" name="Any Stg Placeholder XSmall" GameObjectimage="IGameObjects\PlaceHolderXSmall.png" cansnap="true" collision="true" priority="Medium"></IGameObject>
	<IGameObject id="20" name="Any Stg Placeholder Small" GameObjectimage="IGameObjects\PlaceHolderSmall.png" cansnap="true" collision="true" priority="Medium"></IGameObject>
	<IGameObject id="21" name="Any Stg Placeholder Medium" GameObjectimage="IGameObjects\PlaceHolderMedium.png" cansnap="true" collision="true" priority="Medium"></IGameObject>
	<IGameObject id="22" name="Any Stg Placeholder Large" GameObjectimage="IGameObjects\PlaceHolderLarge.png" cansnap="true" collision="true" priority="Medium"></IGameObject>	
	<IGameObject id="23" name="Stg00 Snow-Coverted Tree" GameObjectimage="IGameObjects\Stg00\SnowCoveredTree.png" gravity="true" priority="BG1" issentient="true"></IGameObject>
	<IGameObject id="24" name="Spring (Left)" GameObjectimage="IGameObjects\SpringLeft.png" cansnap="false" gravity="false"></IGameObject>
	<IGameObject id="25" name="Spring (Right)" GameObjectimage="IGameObjects\SpringRight.png" cansnap="false" gravity="false"></IGameObject>
</IGameObjects>